xcli/__init__.py
xcli/_autocomplete.py
xcli/_exception.py
xcli/_input.py
xcli/_output.py
xcli/_parser.py
xcli/colors.py
xcli-0.2.dist-info/LICENSE
xcli-0.2.dist-info/METADATA
xcli-0.2.dist-info/WHEEL
xcli-0.2.dist-info/top_level.txt
xcli-0.2.dist-info/RECORD
