Metadata-Version: 2.1
Name: xcli
Version: 0.2
Summary: Utilities for building command-line applications
Home-page: UNKNOWN
Author: Ian Fisher
Author-email: iafisher@fastmail.com
License: MIT
Project-URL: Source, https://github.com/iafisher/xcli
Platform: UNKNOWN
Classifier: Programming Language :: Python :: 3
Classifier: License :: OSI Approved :: MIT License
Classifier: Natural Language :: English
